better_experimentation/__init__.py
better_experimentation/better_experimentation.py
better_experimentation/controller/__init__.py
better_experimentation/controller/console.py
better_experimentation/model/ab_test_results.py
better_experimentation/model/ml_model.py
better_experimentation/model/report.py
better_experimentation/repository/ab_test_repository.py
better_experimentation/repository/general_model_repository.py
better_experimentation/repository/interfaces/data_file_repository.py
better_experimentation/repository/interfaces/model_repository.py
better_experimentation/repository/pandas_data_file_repository.py
better_experimentation/repository/sklearn_model_repository.py
better_experimentation/service/ab_pipeline_service.py
better_experimentation/service/experimental_pipeline_service.py
better_experimentation/service/generate_score_service.py
better_experimentation/service/load_model_service.py
better_experimentation/service/load_test_data_service.py
better_experimentation/service/prepare_experiment_service.py
better_experimentation/service/report_generator_service.py
better_experimentation/templates/report.html
better_experimentation/utils/log_config.py
better_experimentation-1.0.2.dist-info/LICENSE
better_experimentation-1.0.2.dist-info/METADATA
better_experimentation-1.0.2.dist-info/WHEEL
better_experimentation-1.0.2.dist-info/entry_points.txt
better_experimentation-1.0.2.dist-info/RECORD
